{
  "schema_version": 3,
  "generated_at": "2026-06-13T12:00:31.552249+08:00",
  "source": "local_v8_4_regression_inference_for_github_pages",
  "model_version": "v9.4a",
  "symbol": "BTCUSDT",
  "interval": "1h",
  "market": "USD-M Futures",
  "max_horizon_bars": 12,
  "horizon_bar_multiples": [
    12
  ],
  "forecasts": [
    {
      "horizon": "12bar",
      "horizon_bars": 12,
      "target_time": "2026-06-13T16:00:00+00:00",
      "prob_up": 0.4857265406847,
      "prob_up_source": "calibrated_dual_head",
      "direction": "up",
      "direction_source": "median_12bar_return",
      "is_actionable": false,
      "confidence": 0.028546918630599993,
      "relative_confidence": 0.028546918630599993,
      "confidence_gate": 0.2,
      "scenario_price": 63571.119140625,
      "scenario_return_pct": 0.1230358317058533,
      "sample_return_pct_median": 0.1230358317058533,
      "sample_return_pct_p10": 0.09415038862551572,
      "sample_return_pct_p90": 0.16665284460492646
    }
  ],
  "evaluation": {
    "h1": {
      "split": "test",
      "horizon": "h1",
      "source": "v9.4a_test_rollout_h1_dual_head_average",
      "samples": 500,
      "start_time": "2025-07-19T02:00:00+00:00",
      "end_time": "2025-08-08T21:00:00+00:00",
      "direction_accuracy": 0.7623574144486692,
      "classification_head_accuracy": 0.7604562737642585,
      "regression_head_accuracy": 0.7642585551330798,
      "classification_head_accuracy_pct": 76.04562737642586,
      "regression_head_accuracy_pct": 76.42585551330798,
      "direction_accuracy_pct": 76.23574144486692,
      "all_horizon_classification_mean_pct": 53.24838211007412,
      "all_horizon_regression_mean_pct": 54.450517532741856,
      "active_sample_ratio": 0.5265,
      "deadzone_threshold": 0.0015,
      "classification_by_horizon_pct": [
        76.04562737642586,
        65.0190114068441,
        52.65151515151515,
        49.42965779467681,
        49.049429657794676,
        53.61216730038023,
        49.049429657794676,
        48.28897338403042,
        45.45454545454545,
        49.80988593155893,
        50.57034220532319,
        50.0
      ],
      "regression_by_horizon_pct": [
        76.42585551330798,
        66.53992395437263,
        53.78787878787878,
        51.33079847908745,
        48.669201520912544,
        53.61216730038023,
        52.47148288973384,
        44.866920152091254,
        46.96969696969697,
        53.2319391634981,
        52.09125475285171,
        53.40909090909091
      ],
      "note": "direction_accuracy is the average of h1 classification_head_accuracy and h1 regression_head_accuracy; omitted if either source metric is unavailable."
    },
    "validation_h1": {
      "split": "validation",
      "horizon": "h1",
      "samples": 7692,
      "start_time": "2024-08-24T14:00:00+00:00",
      "end_time": "2025-07-11T01:00:00+00:00",
      "direction_accuracy": 0.6705668226729069,
      "predicted_up_rate": 0.4876495059802392,
      "actual_up_rate": 0.5076703068122725,
      "mape_pct": 0.2949592522626514
    }
  },
  "predicted_price_path": [
    {
      "step": 0,
      "timestamp": "2026-06-13T04:00:00+00:00",
      "price": 63493.0,
      "open": 63494.4,
      "high": 63497.2,
      "low": 63493.0,
      "atr_1x_lower": 63493.0,
      "atr_1x_upper": 63493.0,
      "atr_2x_lower": 63493.0,
      "atr_2x_upper": 63493.0,
      "prob_up": null,
      "return_pct": 0.0,
      "is_anchor": true
    },
    {
      "step": 1,
      "timestamp": "2026-06-13T05:00:00+00:00",
      "price": 63561.029296875,
      "open": 63493.0,
      "high": 63966.092430332195,
      "low": 63493.0,
      "atr_1x_lower": 63493.0,
      "atr_1x_upper": 63569.0205078125,
      "atr_2x_lower": 63413.374460179766,
      "atr_2x_upper": 63702.57747282518,
      "prob_up": 0.735247540473938,
      "return_pct": 0.10714456219582669,
      "is_anchor": false
    },
    {
      "step": 2,
      "timestamp": "2026-06-13T06:00:00+00:00",
      "price": 63567.474609375,
      "open": 63561.029296875,
      "high": 63972.57881766227,
      "low": 63532.19730454156,
      "atr_1x_lower": 63555.94140625,
      "atr_1x_upper": 63579.8037109375,
      "atr_2x_lower": 63419.80479995866,
      "atr_2x_upper": 63709.03713880935,
      "prob_up": 0.4906147825717926,
      "return_pct": 0.11729577965287064,
      "is_anchor": false
    },
    {
      "step": 3,
      "timestamp": "2026-06-13T07:00:00+00:00",
      "price": 63541.83984375,
      "open": 63567.474609375,
      "high": 63946.780686235856,
      "low": 63506.576765145415,
      "atr_1x_lower": 63534.392578125,
      "atr_1x_upper": 63567.474609375,
      "atr_2x_lower": 63394.22958492895,
      "atr_2x_upper": 63683.34528546322,
      "prob_up": 0.3702021431922913,
      "return_pct": 0.07692161931236452,
      "is_anchor": false
    },
    {
      "step": 4,
      "timestamp": "2026-06-13T08:00:00+00:00",
      "price": 63531.298828125,
      "open": 63541.83984375,
      "high": 63936.17249459332,
      "low": 63496.04159934571,
      "atr_1x_lower": 63525.091796875,
      "atr_1x_upper": 63541.83984375,
      "atr_2x_lower": 63383.713056508735,
      "atr_2x_upper": 63672.78079536729,
      "prob_up": 0.41782517969608307,
      "return_pct": 0.06031976458034105,
      "is_anchor": false
    },
    {
      "step": 5,
      "timestamp": "2026-06-13T09:00:00+00:00",
      "price": 63550.95703125,
      "open": 63531.298828125,
      "high": 63955.955975950026,
      "low": 63515.688892985505,
      "atr_1x_lower": 63531.298828125,
      "atr_1x_upper": 63560.7626953125,
      "atr_2x_lower": 63403.32559283438,
      "atr_2x_upper": 63692.48277661901,
      "prob_up": 0.5581413197517395,
      "return_pct": 0.0912809778243373,
      "is_anchor": false
    },
    {
      "step": 6,
      "timestamp": "2026-06-13T10:00:00+00:00",
      "price": 63561.775390625,
      "open": 63550.95703125,
      "high": 63966.84327880495,
      "low": 63526.50124862095,
      "atr_1x_lower": 63550.95703125,
      "atr_1x_upper": 63573.95703125,
      "atr_2x_lower": 63414.11882072387,
      "atr_2x_upper": 63703.325228099704,
      "prob_up": 0.5242460936307907,
      "return_pct": 0.10831964251964976,
      "is_anchor": false
    },
    {
      "step": 7,
      "timestamp": "2026-06-13T11:00:00+00:00",
      "price": 63560.70703125,
      "open": 63561.775390625,
      "high": 63965.76811096569,
      "low": 63525.43348214098,
      "atr_1x_lower": 63550.9033203125,
      "atr_1x_upper": 63573.421875,
      "atr_2x_lower": 63413.05294319082,
      "atr_2x_upper": 63702.25448952597,
      "prob_up": 0.46930625796318054,
      "return_pct": 0.10663700132298448,
      "is_anchor": false
    },
    {
      "step": 8,
      "timestamp": "2026-06-13T12:00:00+00:00",
      "price": 63559.837890625,
      "open": 63560.70703125,
      "high": 63964.89343146209,
      "low": 63524.56482385288,
      "atr_1x_lower": 63549.951171875,
      "atr_1x_upper": 63572.5732421875,
      "atr_2x_lower": 63412.18582161457,
      "atr_2x_upper": 63701.383413355376,
      "prob_up": 0.4658803844451904,
      "return_pct": 0.10526812502953398,
      "is_anchor": false
    },
    {
      "step": 9,
      "timestamp": "2026-06-13T13:00:00+00:00",
      "price": 63561.759765625,
      "open": 63559.837890625,
      "high": 63966.8275542296,
      "low": 63526.48563229218,
      "atr_1x_lower": 63551.3974609375,
      "atr_1x_upper": 63574.7099609375,
      "atr_2x_lower": 63414.10323202137,
      "atr_2x_upper": 63703.30956830338,
      "prob_up": 0.4781075966358185,
      "return_pct": 0.1082950335076216,
      "is_anchor": false
    },
    {
      "step": 10,
      "timestamp": "2026-06-13T14:00:00+00:00",
      "price": 63565.779296875,
      "open": 63561.759765625,
      "high": 63970.87270123726,
      "low": 63530.502932869495,
      "atr_1x_lower": 63554.6142578125,
      "atr_1x_upper": 63579.4912109375,
      "atr_2x_lower": 63418.11342573803,
      "atr_2x_upper": 63707.33805090805,
      "prob_up": 0.49133554100990295,
      "return_pct": 0.11462570184901377,
      "is_anchor": false
    },
    {
      "step": 11,
      "timestamp": "2026-06-13T15:00:00+00:00",
      "price": 63568.810546875,
      "open": 63565.779296875,
      "high": 63973.92326885431,
      "low": 63533.5325006518,
      "atr_1x_lower": 63557.1103515625,
      "atr_1x_upper": 63583.2529296875,
      "atr_2x_lower": 63421.13763402192,
      "atr_2x_upper": 63710.37605139516,
      "prob_up": 0.4885509717464447,
      "return_pct": 0.11939985018032395,
      "is_anchor": false
    },
    {
      "step": 12,
      "timestamp": "2026-06-13T16:00:00+00:00",
      "price": 63571.119140625,
      "open": 63568.810546875,
      "high": 63976.24657486163,
      "low": 63535.83981322828,
      "atr_1x_lower": 63559.0048828125,
      "atr_1x_upper": 63586.1123046875,
      "atr_2x_lower": 63423.44086481546,
      "atr_2x_upper": 63712.68978630221,
      "prob_up": 0.4857265406847,
      "return_pct": 0.1230358317058533,
      "is_anchor": false
    }
  ],
  "runtime": {
    "samples": 50,
    "temperature": 0.8,
    "noise_std": 0.05,
    "last_close": 63493.0,
    "source_data_path": "btc_BTCUSDT_1h_v9.4a.csv",
    "source_data_start_time": "2020-06-08T06:00:00+00:00",
    "source_data_end_time": "2026-06-07T06:00:00+00:00",
    "source_data_rows_1h": 52561,
    "inference_source": "local_v8_4_csv_plus_binance_recent",
    "inference_context_start_time": "2026-06-10T13:00:00+00:00",
    "inference_context_end_time": "2026-06-13T04:00:00+00:00",
    "fetched_start_time": "2020-06-08T06:00:00+00:00",
    "fetched_end_time": "2026-06-13T04:00:00+00:00",
    "fetched_rows_1h": 52703,
    "fetched_rows_4h": 13177,
    "live_fetch_start_time": "2026-06-03T05:00:00+00:00",
    "live_fetch_end_time": "2026-06-13T04:00:00+00:00",
    "live_fetch_rows_1h": 240,
    "last_kline_time": "2026-06-13T04:00:00+00:00",
    "model_type": "BTCRegressionModel_v9.4a_dual_head_regime",
    "calib_temp": 1.0577880855525867,
    "regime_features": [
      "mvrv_z",
      "mvrv_z_pct",
      "mayer",
      "mayer_pct",
      "adx14",
      "adx_slope",
      "atr_pct",
      "atr_pct_pct"
    ],
    "true_lr_std_scaled": 0.9994555711746216,
    "recent_raw_logret_std": 0.004419930744916201,
    "probability_note": "v9.4a is a one-step dual-head model; prob_up comes from the temperature-calibrated direction head averaged over sampled autoregressive paths."
  }
}