{
  "schema_version": 3,
  "generated_at": "2026-06-02T19:43:23.463683+08:00",
  "source": "local_v8_4_regression_inference_for_github_pages",
  "model_version": "v9.4a",
  "symbol": "BTCUSDT",
  "interval": "1h",
  "market": "USD-M Futures",
  "max_horizon_bars": 12,
  "horizon_bar_multiples": [
    12
  ],
  "forecasts": [
    {
      "horizon": "12bar",
      "horizon_bars": 12,
      "target_time": "2026-06-02T23:00:00+00:00",
      "prob_up": 0.21881214112043382,
      "prob_up_source": "calibrated_dual_head",
      "direction": "down",
      "direction_source": "median_12bar_return",
      "is_actionable": true,
      "confidence": 0.5623757177591324,
      "relative_confidence": 0.5623757177591324,
      "confidence_gate": 0.7,
      "scenario_price": 68629.16796875,
      "scenario_return_pct": -1.197125901768914,
      "sample_return_pct_median": -1.197125901768914,
      "sample_return_pct_p10": -1.2726283531550853,
      "sample_return_pct_p90": -1.1377701707584242
    }
  ],
  "evaluation": {
    "h1": {
      "split": "validation",
      "horizon": "h1",
      "samples": 7692,
      "start_time": "2024-08-19T19:00:00+00:00",
      "end_time": "2025-07-06T06:00:00+00:00",
      "direction_accuracy": 0.6764170566822673,
      "predicted_up_rate": 0.5478419136765471,
      "actual_up_rate": 0.5071502860114404,
      "mape_pct": 0.2927193254011988
    }
  },
  "predicted_price_path": [
    {
      "step": 0,
      "timestamp": "2026-06-02T11:00:00+00:00",
      "price": 69460.7,
      "open": 69620.9,
      "high": 69635.0,
      "low": 69364.1,
      "atr_1x_lower": 69460.7,
      "atr_1x_upper": 69460.7,
      "atr_2x_lower": 69460.7,
      "atr_2x_upper": 69460.7,
      "prob_up": null,
      "return_pct": 0.0,
      "is_anchor": true
    },
    {
      "step": 1,
      "timestamp": "2026-06-02T12:00:00+00:00",
      "price": 69259.8984375,
      "open": 69460.7,
      "high": 69693.05380483081,
      "low": 69221.5935117881,
      "atr_1x_lower": 69244.095703125,
      "atr_1x_upper": 69460.7,
      "atr_2x_lower": 69100.3898822618,
      "atr_2x_upper": 69460.7,
      "prob_up": 0.15373723402619363,
      "return_pct": -0.289086580613207,
      "is_anchor": false
    },
    {
      "step": 2,
      "timestamp": "2026-06-02T13:00:00+00:00",
      "price": 69044.33203125,
      "open": 69259.8984375,
      "high": 69476.13923394312,
      "low": 69006.14632683879,
      "atr_1x_lower": 69019.482421875,
      "atr_1x_upper": 69259.8984375,
      "atr_2x_lower": 68885.31993481112,
      "atr_2x_upper": 69259.8984375,
      "prob_up": 0.14711458548903467,
      "return_pct": -0.5994295605284639,
      "is_anchor": false
    },
    {
      "step": 3,
      "timestamp": "2026-06-02T14:00:00+00:00",
      "price": 68940.73828125,
      "open": 69044.33203125,
      "high": 69371.8976027038,
      "low": 68902.6098704674,
      "atr_1x_lower": 68914.9765625,
      "atr_1x_upper": 69044.33203125,
      "atr_2x_lower": 68781.96476571822,
      "atr_2x_upper": 69090.54470627171,
      "prob_up": 0.30592764139175416,
      "return_pct": -0.7485696498163663,
      "is_anchor": false
    },
    {
      "step": 4,
      "timestamp": "2026-06-02T15:00:00+00:00",
      "price": 68882.94140625,
      "open": 68940.73828125,
      "high": 69313.73926274087,
      "low": 68844.8449606457,
      "atr_1x_lower": 68865.455078125,
      "atr_1x_upper": 68940.73828125,
      "atr_2x_lower": 68724.30099943244,
      "atr_2x_upper": 69032.62224017076,
      "prob_up": 0.37613885700702665,
      "return_pct": -0.8317776724824255,
      "is_anchor": false
    },
    {
      "step": 5,
      "timestamp": "2026-06-02T16:00:00+00:00",
      "price": 68938.25390625,
      "open": 68882.94140625,
      "high": 69369.39769028041,
      "low": 68882.94140625,
      "atr_1x_lower": 68882.94140625,
      "atr_1x_upper": 68952.6875,
      "atr_2x_lower": 68779.48611234178,
      "atr_2x_upper": 69088.05493278969,
      "prob_up": 0.5771092939376831,
      "return_pct": -0.7521463125911398,
      "is_anchor": false
    },
    {
      "step": 6,
      "timestamp": "2026-06-02T17:00:00+00:00",
      "price": 68870.7421875,
      "open": 68938.25390625,
      "high": 69301.46374937886,
      "low": 68832.65248880377,
      "atr_1x_lower": 68844.44921875,
      "atr_1x_upper": 68938.25390625,
      "atr_2x_lower": 68712.12987601325,
      "atr_2x_upper": 69020.3965128368,
      "prob_up": 0.2637085095047951,
      "return_pct": -0.8493404363906443,
      "is_anchor": false
    },
    {
      "step": 7,
      "timestamp": "2026-06-02T18:00:00+00:00",
      "price": 68747.8515625,
      "open": 68870.7421875,
      "high": 69177.80455937929,
      "low": 68709.82982977496,
      "atr_1x_lower": 68718.94921875,
      "atr_1x_upper": 68870.7421875,
      "atr_2x_lower": 68589.52227346184,
      "atr_2x_upper": 68897.23884971597,
      "prob_up": 0.14348976582288742,
      "return_pct": -1.026261522702765,
      "is_anchor": false
    },
    {
      "step": 8,
      "timestamp": "2026-06-02T19:00:00+00:00",
      "price": 68659.48828125,
      "open": 68747.8515625,
      "high": 69088.88864911291,
      "low": 68621.51541878033,
      "atr_1x_lower": 68632.259765625,
      "atr_1x_upper": 68747.8515625,
      "atr_2x_lower": 68501.3624966877,
      "atr_2x_upper": 68808.68355736198,
      "prob_up": 0.22483157068490983,
      "return_pct": -1.153474869602522,
      "is_anchor": false
    },
    {
      "step": 9,
      "timestamp": "2026-06-02T20:00:00+00:00",
      "price": 68714.42578125,
      "open": 68659.48828125,
      "high": 69144.16973138099,
      "low": 68659.48828125,
      "atr_1x_lower": 68659.48828125,
      "atr_1x_upper": 68730.609375,
      "atr_2x_lower": 68556.17347323832,
      "atr_2x_upper": 68863.74043511567,
      "prob_up": 0.6495436811447144,
      "return_pct": -1.0743833833376293,
      "is_anchor": false
    },
    {
      "step": 10,
      "timestamp": "2026-06-02T21:00:00+00:00",
      "price": 68726.05859375,
      "open": 68714.42578125,
      "high": 69155.87529615591,
      "low": 68688.04891385882,
      "atr_1x_lower": 68695.9140625,
      "atr_1x_upper": 68743.20703125,
      "atr_2x_lower": 68567.77949486572,
      "atr_2x_upper": 68875.39852541364,
      "prob_up": 0.48256442725658416,
      "return_pct": -1.0576360535525797,
      "is_anchor": false
    },
    {
      "step": 11,
      "timestamp": "2026-06-02T22:00:00+00:00",
      "price": 68682.82421875,
      "open": 68726.05859375,
      "high": 69112.37053090113,
      "low": 68644.83845009115,
      "atr_1x_lower": 68649.2109375,
      "atr_1x_upper": 68726.05859375,
      "atr_2x_lower": 68524.64469050975,
      "atr_2x_upper": 68832.07020324512,
      "prob_up": 0.25052003771066667,
      "return_pct": -1.1198789837274847,
      "is_anchor": false
    },
    {
      "step": 12,
      "timestamp": "2026-06-02T23:00:00+00:00",
      "price": 68629.16796875,
      "open": 68682.82421875,
      "high": 69058.37871164383,
      "low": 68591.21187525263,
      "atr_1x_lower": 68593.689453125,
      "atr_1x_upper": 68682.82421875,
      "atr_2x_lower": 68471.11201318471,
      "atr_2x_upper": 68778.29735961424,
      "prob_up": 0.21881214112043382,
      "return_pct": -1.197125901768914,
      "is_anchor": false
    }
  ],
  "runtime": {
    "samples": 50,
    "temperature": 0.8,
    "noise_std": 0.05,
    "last_close": 69460.7,
    "source_data_path": "btc_BTCUSDT_1h_v8.6.csv",
    "source_data_start_time": "2020-06-03T11:00:00+00:00",
    "source_data_end_time": "2026-06-02T11:00:00+00:00",
    "source_data_rows_1h": 52561,
    "inference_source": "local_v8_4_csv_plus_binance_recent",
    "inference_context_start_time": "2026-05-30T20:00:00+00:00",
    "inference_context_end_time": "2026-06-02T11:00:00+00:00",
    "fetched_start_time": "2020-06-03T11:00:00+00:00",
    "fetched_end_time": "2026-06-02T11:00:00+00:00",
    "fetched_rows_1h": 52561,
    "fetched_rows_4h": 13141,
    "live_fetch_start_time": "2026-05-23T12:00:00+00:00",
    "live_fetch_end_time": "2026-06-02T11:00:00+00:00",
    "live_fetch_rows_1h": 240,
    "last_kline_time": "2026-06-02T11:00:00+00:00",
    "model_type": "BTCRegressionModel_v9.4a_dual_head_regime",
    "calib_temp": 1.0648249141020334,
    "regime_features": [
      "mvrv_z",
      "mvrv_z_pct",
      "mayer",
      "mayer_pct",
      "adx14",
      "adx_slope",
      "atr_pct",
      "atr_pct_pct"
    ],
    "true_lr_std_scaled": 1.0,
    "recent_raw_logret_std": 0.003165631089359522,
    "probability_note": "v9.4a is a one-step dual-head model; prob_up comes from the temperature-calibrated direction head averaged over sampled autoregressive paths."
  }
}